{
  "unconverted": {
    "8to10": {
      "n": 145845,
      "iso_cut": 0.8918273999999999,
      "n_pass_iso03": 81289,
      "pass_frac_iso03": 0.557365696458569,
      "mean_cluster_iso_03": 0.8812481164932251,
      "median_cluster_iso_03": 0.7900310158729553,
      "mean_cluster_iso_03_emcal": 4.647722244262695,
      "median_cluster_iso_03_emcal": 4.696660995483398,
      "mean_cluster_iso_03_hcalin": 0.31429407000541687,
      "median_cluster_iso_03_hcalin": 0.22341246902942657,
      "mean_cluster_iso_03_hcalout": 0.31748706102371216,
      "median_cluster_iso_03_hcalout": 0.22378471493721008,
      "mean_cluster_iso_04": 1.0294463634490967,
      "median_cluster_iso_04": 0.9275985956192017,
      "mean_cluster_iso_04_emcal": 8.096197128295898,
      "median_cluster_iso_04_emcal": 8.244302749633789,
      "mean_cluster_iso_04_hcalin": 0.344704270362854,
      "median_cluster_iso_04_hcalin": 0.2523961365222931,
      "mean_cluster_iso_04_hcalout": 0.46782463788986206,
      "median_cluster_iso_04_hcalout": 0.3616887927055359,
      "n_exact": 145845,
      "n_pass_exact": 81967,
      "pass_frac_exact": 0.5620144674140355,
      "mean_cluster_Et": 9.189634543522233
    },
    "10to12": {
      "n": 204869,
      "iso_cut": 0.9784345999999999,
      "n_pass_iso03": 138267,
      "pass_frac_iso03": 0.6749044511370681,
      "mean_cluster_iso_03": 0.7388264536857605,
      "median_cluster_iso_03": 0.675336480140686,
      "mean_cluster_iso_03_emcal": 4.689476013183594,
      "median_cluster_iso_03_emcal": 4.7279253005981445,
      "mean_cluster_iso_03_hcalin": 0.22472821176052094,
      "median_cluster_iso_03_hcalin": 0.1599675714969635,
      "mean_cluster_iso_03_hcalout": 0.2626669406890869,
      "median_cluster_iso_03_hcalout": 0.19713766872882843,
      "mean_cluster_iso_04": 0.8752131462097168,
      "median_cluster_iso_04": 0.7928245067596436,
      "mean_cluster_iso_04_emcal": 8.180660247802734,
      "median_cluster_iso_04_emcal": 8.301456451416016,
      "mean_cluster_iso_04_hcalin": 0.2524408996105194,
      "median_cluster_iso_04_hcalin": 0.18579082190990448,
      "mean_cluster_iso_04_hcalout": 0.40795937180519104,
      "median_cluster_iso_04_hcalout": 0.32834675908088684,
      "n_exact": 204869,
      "n_pass_exact": 137815,
      "pass_frac_exact": 0.6726981632164944,
      "mean_cluster_Et": 10.910447041768155
    },
    "12to14": {
      "n": 93313,
      "iso_cut": 1.0650418,
      "n_pass_iso03": 64822,
      "pass_frac_iso03": 0.6946727679958848,
      "mean_cluster_iso_03": 0.7884560823440552,
      "median_cluster_iso_03": 0.720386803150177,
      "mean_cluster_iso_03_emcal": 4.699713230133057,
      "median_cluster_iso_03_emcal": 4.737795829772949,
      "mean_cluster_iso_03_hcalin": 0.2489306628704071,
      "median_cluster_iso_03_hcalin": 0.1785556823015213,
      "mean_cluster_iso_03_hcalout": 0.2737724483013153,
      "median_cluster_iso_03_hcalout": 0.20357197523117065,
      "mean_cluster_iso_04": 0.9283372759819031,
      "median_cluster_iso_04": 0.8416184186935425,
      "mean_cluster_iso_04_emcal": 8.20146656036377,
      "median_cluster_iso_04_emcal": 8.32164478302002,
      "mean_cluster_iso_04_hcalin": 0.2770342528820038,
      "median_cluster_iso_04_hcalin": 0.2047329843044281,
      "mean_cluster_iso_04_hcalout": 0.419840008020401,
      "median_cluster_iso_04_hcalout": 0.3362520635128021,
      "n_exact": 93313,
      "n_pass_exact": 64516,
      "pass_frac_exact": 0.6913934821514687,
      "mean_cluster_Et": 12.855550673539593
    },
    "14to16": {
      "n": 39375,
      "iso_cut": 1.151649,
      "n_pass_iso03": 27508,
      "pass_frac_iso03": 0.698615873015873,
      "mean_cluster_iso_03": 0.8686757683753967,
      "median_cluster_iso_03": 0.7904163002967834,
      "mean_cluster_iso_03_emcal": 4.707600116729736,
      "median_cluster_iso_03_emcal": 4.745208740234375,
      "mean_cluster_iso_03_hcalin": 0.29091164469718933,
      "median_cluster_iso_03_hcalin": 0.20754387974739075,
      "mean_cluster_iso_03_hcalout": 0.2918156683444977,
      "median_cluster_iso_03_hcalout": 0.21468552947044373,
      "mean_cluster_iso_04": 1.0085556507110596,
      "median_cluster_iso_04": 0.9098893404006958,
      "mean_cluster_iso_04_emcal": 8.208619117736816,
      "median_cluster_iso_04_emcal": 8.32099723815918,
      "mean_cluster_iso_04_hcalin": 0.31953778862953186,
      "median_cluster_iso_04_hcalin": 0.23440571129322052,
      "mean_cluster_iso_04_hcalout": 0.4400065541267395,
      "median_cluster_iso_04_hcalout": 0.35010987520217896,
      "n_exact": 39375,
      "n_pass_exact": 27376,
      "pass_frac_exact": 0.695263492063492,
      "mean_cluster_Et": 14.861923809523809
    },
    "16to18": {
      "n": 17630,
      "iso_cut": 1.2382562,
      "n_pass_iso03": 12332,
      "pass_frac_iso03": 0.6994895065229723,
      "mean_cluster_iso_03": 0.951695442199707,
      "median_cluster_iso_03": 0.8594968914985657,
      "mean_cluster_iso_03_emcal": 4.718191623687744,
      "median_cluster_iso_03_emcal": 4.757840156555176,
      "mean_cluster_iso_03_hcalin": 0.329407274723053,
      "median_cluster_iso_03_hcalin": 0.23938433825969696,
      "mean_cluster_iso_03_hcalout": 0.3111775517463684,
      "median_cluster_iso_03_hcalout": 0.2279435098171234,
      "mean_cluster_iso_04": 1.0900400876998901,
      "median_cluster_iso_04": 0.9855634570121765,
      "mean_cluster_iso_04_emcal": 8.218729972839355,
      "median_cluster_iso_04_emcal": 8.331022262573242,
      "mean_cluster_iso_04_hcalin": 0.3588828146457672,
      "median_cluster_iso_04_hcalin": 0.26587820053100586,
      "mean_cluster_iso_04_hcalout": 0.4609648287296295,
      "median_cluster_iso_04_hcalout": 0.3659680485725403,
      "n_exact": 17630,
      "n_pass_exact": 12276,
      "pass_frac_exact": 0.6963131026659104,
      "mean_cluster_Et": 16.86251550978446
    },
    "18to20": {
      "n": 8387,
      "iso_cut": 1.3248634,
      "n_pass_iso03": 5927,
      "pass_frac_iso03": 0.7066889233337308,
      "mean_cluster_iso_03": 1.0141767263412476,
      "median_cluster_iso_03": 0.9226916432380676,
      "mean_cluster_iso_03_emcal": 4.728285789489746,
      "median_cluster_iso_03_emcal": 4.767366409301758,
      "mean_cluster_iso_03_hcalin": 0.36196210980415344,
      "median_cluster_iso_03_hcalin": 0.2662850022315979,
      "mean_cluster_iso_03_hcalout": 0.32887282967567444,
      "median_cluster_iso_03_hcalout": 0.23794539272785187,
      "mean_cluster_iso_04": 1.1668099164962769,
      "median_cluster_iso_04": 1.053412675857544,
      "mean_cluster_iso_04_emcal": 8.247329711914062,
      "median_cluster_iso_04_emcal": 8.358644485473633,
      "mean_cluster_iso_04_hcalin": 0.39144542813301086,
      "median_cluster_iso_04_hcalin": 0.29369327425956726,
      "mean_cluster_iso_04_hcalout": 0.4806405007839203,
      "median_cluster_iso_04_hcalout": 0.3783680498600006,
      "n_exact": 8387,
      "n_pass_exact": 5929,
      "pass_frac_exact": 0.7069273876237033,
      "mean_cluster_Et": 18.87499254799094
    },
    "20to22": {
      "n": 3944,
      "iso_cut": 1.4114706,
      "n_pass_iso03": 2847,
      "pass_frac_iso03": 0.7218559837728195,
      "mean_cluster_iso_03": 1.0811690092086792,
      "median_cluster_iso_03": 0.9945516586303711,
      "mean_cluster_iso_03_emcal": 4.748956203460693,
      "median_cluster_iso_03_emcal": 4.78304386138916,
      "mean_cluster_iso_03_hcalin": 0.4010307788848877,
      "median_cluster_iso_03_hcalin": 0.30196914076805115,
      "mean_cluster_iso_03_hcalout": 0.34185555577278137,
      "median_cluster_iso_03_hcalout": 0.25080180168151855,
      "mean_cluster_iso_04": 1.2183973789215088,
      "median_cluster_iso_04": 1.112088680267334,
      "mean_cluster_iso_04_emcal": 8.265564918518066,
      "median_cluster_iso_04_emcal": 8.361285209655762,
      "mean_cluster_iso_04_hcalin": 0.4320175349712372,
      "median_cluster_iso_04_hcalin": 0.3306195139884949,
      "mean_cluster_iso_04_hcalout": 0.4955979883670807,
      "median_cluster_iso_04_hcalout": 0.3892331123352051,
      "n_exact": 3944,
      "n_pass_exact": 2832,
      "pass_frac_exact": 0.718052738336714,
      "mean_cluster_Et": 20.89062450478575
    },
    "22to24": {
      "n": 2031,
      "iso_cut": 1.4980778,
      "n_pass_iso03": 1485,
      "pass_frac_iso03": 0.7311669128508124,
      "mean_cluster_iso_03": 1.1630570888519287,
      "median_cluster_iso_03": 1.0500952005386353,
      "mean_cluster_iso_03_emcal": 4.737298488616943,
      "median_cluster_iso_03_emcal": 4.764505386352539,
      "mean_cluster_iso_03_hcalin": 0.44785457849502563,
      "median_cluster_iso_03_hcalin": 0.3355250060558319,
      "mean_cluster_iso_03_hcalout": 0.370993971824646,
      "median_cluster_iso_03_hcalout": 0.2647382318973541,
      "mean_cluster_iso_04": 1.303667664527893,
      "median_cluster_iso_04": 1.1627498865127563,
      "mean_cluster_iso_04_emcal": 8.238689422607422,
      "median_cluster_iso_04_emcal": 8.34160041809082,
      "mean_cluster_iso_04_hcalin": 0.47924256324768066,
      "median_cluster_iso_04_hcalin": 0.3646314740180969,
      "mean_cluster_iso_04_hcalout": 0.5302349925041199,
      "median_cluster_iso_04_hcalout": 0.40934085845947266,
      "n_exact": 2031,
      "n_pass_exact": 1483,
      "pass_frac_exact": 0.7301821762678483,
      "mean_cluster_Et": 22.90018531126908
    },
    "24to26": {
      "n": 1021,
      "iso_cut": 1.584685,
      "n_pass_iso03": 727,
      "pass_frac_iso03": 0.7120470127326151,
      "mean_cluster_iso_03": 1.2507045269012451,
      "median_cluster_iso_03": 1.1055189371109009,
      "mean_cluster_iso_03_emcal": 4.742810249328613,
      "median_cluster_iso_03_emcal": 4.781818389892578,
      "mean_cluster_iso_03_hcalin": 0.49888312816619873,
      "median_cluster_iso_03_hcalin": 0.36403313279151917,
      "mean_cluster_iso_03_hcalout": 0.3926876485347748,
      "median_cluster_iso_03_hcalout": 0.28258615732192993,
      "mean_cluster_iso_04": 1.402259111404419,
      "median_cluster_iso_04": 1.2042346000671387,
      "mean_cluster_iso_04_emcal": 8.261883735656738,
      "median_cluster_iso_04_emcal": 8.344614028930664,
      "mean_cluster_iso_04_hcalin": 0.5297495722770691,
      "median_cluster_iso_04_hcalin": 0.39379459619522095,
      "mean_cluster_iso_04_hcalout": 0.547701358795166,
      "median_cluster_iso_04_hcalout": 0.4227864146232605,
      "n_exact": 1021,
      "n_pass_exact": 723,
      "pass_frac_exact": 0.7081292850146915,
      "mean_cluster_Et": 24.890807687010284
    },
    "26to28": {
      "n": 553,
      "iso_cut": 1.6712922,
      "n_pass_iso03": 406,
      "pass_frac_iso03": 0.7341772151898734,
      "mean_cluster_iso_03": 1.3053579330444336,
      "median_cluster_iso_03": 1.1702895164489746,
      "mean_cluster_iso_03_emcal": 4.772794723510742,
      "median_cluster_iso_03_emcal": 4.808475494384766,
      "mean_cluster_iso_03_hcalin": 0.5192554593086243,
      "median_cluster_iso_03_hcalin": 0.39048540592193604,
      "mean_cluster_iso_03_hcalout": 0.4030218720436096,
      "median_cluster_iso_03_hcalout": 0.2937741279602051,
      "mean_cluster_iso_04": 1.45357084274292,
      "median_cluster_iso_04": 1.2905330657958984,
      "mean_cluster_iso_04_emcal": 8.293286323547363,
      "median_cluster_iso_04_emcal": 8.41061019897461,
      "mean_cluster_iso_04_hcalin": 0.5514248609542847,
      "median_cluster_iso_04_hcalin": 0.4171407222747803,
      "mean_cluster_iso_04_hcalout": 0.5647206902503967,
      "median_cluster_iso_04_hcalout": 0.44748276472091675,
      "n_exact": 553,
      "n_pass_exact": 404,
      "pass_frac_exact": 0.7305605786618445,
      "mean_cluster_Et": 26.880222313658454
    },
    "28to32": {
      "n": 403,
      "iso_cut": 1.8012029999999999,
      "n_pass_iso03": 292,
      "pass_frac_iso03": 0.7245657568238213,
      "mean_cluster_iso_03": 1.431908130645752,
      "median_cluster_iso_03": 1.227872610092163,
      "mean_cluster_iso_03_emcal": 4.798167705535889,
      "median_cluster_iso_03_emcal": 4.803537368774414,
      "mean_cluster_iso_03_hcalin": 0.5691772699356079,
      "median_cluster_iso_03_hcalin": 0.4423859417438507,
      "mean_cluster_iso_03_hcalout": 0.4350093603134155,
      "median_cluster_iso_03_hcalout": 0.30649334192276,
      "mean_cluster_iso_04": 1.5749633312225342,
      "median_cluster_iso_04": 1.4213403463363647,
      "mean_cluster_iso_04_emcal": 8.326356887817383,
      "median_cluster_iso_04_emcal": 8.40093994140625,
      "mean_cluster_iso_04_hcalin": 0.6022120118141174,
      "median_cluster_iso_04_hcalin": 0.4712585210800171,
      "mean_cluster_iso_04_hcalout": 0.5899896025657654,
      "median_cluster_iso_04_hcalout": 0.4581073820590973,
      "n_exact": 403,
      "n_pass_exact": 288,
      "pass_frac_exact": 0.7146401985111662,
      "mean_cluster_Et": 29.55133859336228
    },
    "32to36": {
      "n": 101,
      "iso_cut": 1.9744173999999999,
      "n_pass_iso03": 78,
      "pass_frac_iso03": 0.7722772277227723,
      "mean_cluster_iso_03": 1.3156547546386719,
      "median_cluster_iso_03": 1.3257083892822266,
      "mean_cluster_iso_03_emcal": 4.675504207611084,
      "median_cluster_iso_03_emcal": 4.767585754394531,
      "mean_cluster_iso_03_hcalin": 0.5980963706970215,
      "median_cluster_iso_03_hcalin": 0.5261264443397522,
      "mean_cluster_iso_03_hcalout": 0.41008979082107544,
      "median_cluster_iso_03_hcalout": 0.34253454208374023,
      "mean_cluster_iso_04": 1.5074633359909058,
      "median_cluster_iso_04": 1.4856542348861694,
      "mean_cluster_iso_04_emcal": 8.192923545837402,
      "median_cluster_iso_04_emcal": 8.359256744384766,
      "mean_cluster_iso_04_hcalin": 0.6253962516784668,
      "median_cluster_iso_04_hcalin": 0.5436347126960754,
      "mean_cluster_iso_04_hcalout": 0.587402880191803,
      "median_cluster_iso_04_hcalout": 0.46983054280281067,
      "n_exact": 101,
      "n_pass_exact": 78,
      "pass_frac_exact": 0.7722772277227723,
      "mean_cluster_Et": 33.52537914313892
    },
    "8to36": {
      "n": 517472,
      "iso_cut": 1.1083454,
      "n_pass_iso03": 362677,
      "pass_frac_iso03": 0.7008630418650671,
      "mean_cluster_iso_03": 0.8160536289215088,
      "median_cluster_iso_03": 0.7388204336166382,
      "mean_cluster_iso_03_emcal": 4.683457374572754,
      "median_cluster_iso_03_emcal": 4.72501277923584,
      "mean_cluster_iso_03_hcalin": 0.2685787081718445,
      "median_cluster_iso_03_hcalin": 0.1879849135875702,
      "mean_cluster_iso_03_hcalout": 0.28666210174560547,
      "median_cluster_iso_03_hcalout": 0.20857678353786469,
      "mean_cluster_iso_04": 0.9570770859718323,
      "median_cluster_iso_04": 0.8636944890022278,
      "mean_cluster_iso_04_emcal": 8.166382789611816,
      "median_cluster_iso_04_emcal": 8.294791221618652,
      "mean_cluster_iso_04_hcalin": 0.29733482003211975,
      "median_cluster_iso_04_hcalin": 0.21460388600826263,
      "mean_cluster_iso_04_hcalout": 0.43416452407836914,
      "median_cluster_iso_04_hcalout": 0.34260278940200806,
      "n_exact": 517472,
      "n_pass_exact": 335687,
      "pass_frac_exact": 0.6487056304495702,
      "mean_cluster_Et": 11.595449125749798
    }
  },
  "converted": {
    "8to10": {
      "n": 29776,
      "iso_cut": 0.8918273999999999,
      "n_pass_iso03": 9846,
      "pass_frac_iso03": 0.33066899516389037,
      "mean_cluster_iso_03": 1.8469722270965576,
      "median_cluster_iso_03": 1.4112050533294678,
      "mean_cluster_iso_03_emcal": 5.566990375518799,
      "median_cluster_iso_03_emcal": 5.10153865814209,
      "mean_cluster_iso_03_hcalin": 0.21562077105045319,
      "median_cluster_iso_03_hcalin": 0.1543378382921219,
      "mean_cluster_iso_03_hcalout": 0.25823700428009033,
      "median_cluster_iso_03_hcalout": 0.19339688122272491,
      "mean_cluster_iso_04": 1.997972011566162,
      "median_cluster_iso_04": 1.6284770965576172,
      "mean_cluster_iso_04_emcal": 8.871559143066406,
      "median_cluster_iso_04_emcal": 8.683538436889648,
      "mean_cluster_iso_04_hcalin": 0.24451175332069397,
      "median_cluster_iso_04_hcalin": 0.181738942861557,
      "mean_cluster_iso_04_hcalout": 0.40361955761909485,
      "median_cluster_iso_04_hcalout": 0.3258384168148041,
      "n_exact": 29776,
      "n_pass_exact": 9948,
      "pass_frac_exact": 0.334094572810317,
      "mean_cluster_Et": 9.072135486633531
    },
    "10to12": {
      "n": 31455,
      "iso_cut": 0.9784345999999999,
      "n_pass_iso03": 17692,
      "pass_frac_iso03": 0.5624542997933556,
      "mean_cluster_iso_03": 1.1474841833114624,
      "median_cluster_iso_03": 0.8395726680755615,
      "mean_cluster_iso_03_emcal": 4.972226619720459,
      "median_cluster_iso_03_emcal": 4.795609474182129,
      "mean_cluster_iso_03_hcalin": 0.1878485530614853,
      "median_cluster_iso_03_hcalin": 0.13594594597816467,
      "mean_cluster_iso_03_hcalout": 0.24129575490951538,
      "median_cluster_iso_03_hcalout": 0.18645092844963074,
      "mean_cluster_iso_04": 1.2898941040039062,
      "median_cluster_iso_04": 1.0066847801208496,
      "mean_cluster_iso_04_emcal": 8.317329406738281,
      "median_cluster_iso_04_emcal": 8.358202934265137,
      "mean_cluster_iso_04_hcalin": 0.21534381806850433,
      "median_cluster_iso_04_hcalin": 0.1610107570886612,
      "mean_cluster_iso_04_hcalout": 0.38397008180618286,
      "median_cluster_iso_04_hcalout": 0.3153148591518402,
      "n_exact": 31455,
      "n_pass_exact": 17638,
      "pass_frac_exact": 0.5607375615959307,
      "mean_cluster_Et": 10.911246224765538
    },
    "12to14": {
      "n": 14408,
      "iso_cut": 1.0650418,
      "n_pass_iso03": 8742,
      "pass_frac_iso03": 0.6067462520821766,
      "mean_cluster_iso_03": 1.1238224506378174,
      "median_cluster_iso_03": 0.8435251712799072,
      "mean_cluster_iso_03_emcal": 4.917463779449463,
      "median_cluster_iso_03_emcal": 4.770327568054199,
      "mean_cluster_iso_03_hcalin": 0.21031568944454193,
      "median_cluster_iso_03_hcalin": 0.15245068073272705,
      "mean_cluster_iso_03_hcalout": 0.25014376640319824,
      "median_cluster_iso_03_hcalout": 0.19261977076530457,
      "mean_cluster_iso_04": 1.2670739889144897,
      "median_cluster_iso_04": 1.0019294023513794,
      "mean_cluster_iso_04_emcal": 8.26976490020752,
      "median_cluster_iso_04_emcal": 8.33541488647461,
      "mean_cluster_iso_04_hcalin": 0.2385147660970688,
      "median_cluster_iso_04_hcalin": 0.17848628759384155,
      "mean_cluster_iso_04_hcalout": 0.3938392102718353,
      "median_cluster_iso_04_hcalout": 0.3218005299568176,
      "n_exact": 14408,
      "n_pass_exact": 8718,
      "pass_frac_exact": 0.6050805108273182,
      "mean_cluster_Et": 12.858063879441977
    },
    "14to16": {
      "n": 6146,
      "iso_cut": 1.151649,
      "n_pass_iso03": 3891,
      "pass_frac_iso03": 0.6330946957370648,
      "mean_cluster_iso_03": 1.158747673034668,
      "median_cluster_iso_03": 0.890148401260376,
      "mean_cluster_iso_03_emcal": 4.878667831420898,
      "median_cluster_iso_03_emcal": 4.757474422454834,
      "mean_cluster_iso_03_hcalin": 0.2421819120645523,
      "median_cluster_iso_03_hcalin": 0.17545656859874725,
      "mean_cluster_iso_03_hcalout": 0.26657387614250183,
      "median_cluster_iso_03_hcalout": 0.20164233446121216,
      "mean_cluster_iso_04": 1.2920682430267334,
      "median_cluster_iso_04": 1.021714687347412,
      "mean_cluster_iso_04_emcal": 8.215875625610352,
      "median_cluster_iso_04_emcal": 8.301799774169922,
      "mean_cluster_iso_04_hcalin": 0.2703477144241333,
      "median_cluster_iso_04_hcalin": 0.2018863558769226,
      "mean_cluster_iso_04_hcalout": 0.414235919713974,
      "median_cluster_iso_04_hcalout": 0.3338797986507416,
      "n_exact": 6146,
      "n_pass_exact": 3878,
      "pass_frac_exact": 0.6309794988610479,
      "mean_cluster_Et": 14.864598481227628
    },
    "16to18": {
      "n": 2975,
      "iso_cut": 1.2382562,
      "n_pass_iso03": 1918,
      "pass_frac_iso03": 0.6447058823529411,
      "mean_cluster_iso_03": 1.175860047340393,
      "median_cluster_iso_03": 0.9347968697547913,
      "mean_cluster_iso_03_emcal": 4.887608051300049,
      "median_cluster_iso_03_emcal": 4.754583358764648,
      "mean_cluster_iso_03_hcalin": 0.2703748941421509,
      "median_cluster_iso_03_hcalin": 0.1996743083000183,
      "mean_cluster_iso_03_hcalout": 0.2692892849445343,
      "median_cluster_iso_03_hcalout": 0.2078392207622528,
      "mean_cluster_iso_04": 1.3126444816589355,
      "median_cluster_iso_04": 1.0769095420837402,
      "mean_cluster_iso_04_emcal": 8.245043754577637,
      "median_cluster_iso_04_emcal": 8.302021026611328,
      "mean_cluster_iso_04_hcalin": 0.3000014126300812,
      "median_cluster_iso_04_hcalin": 0.22802068293094635,
      "mean_cluster_iso_04_hcalout": 0.4154755473136902,
      "median_cluster_iso_04_hcalout": 0.3426491320133209,
      "n_exact": 2975,
      "n_pass_exact": 1913,
      "pass_frac_exact": 0.6430252100840336,
      "mean_cluster_Et": 16.87725905987395
    },
    "18to20": {
      "n": 1359,
      "iso_cut": 1.3248634,
      "n_pass_iso03": 897,
      "pass_frac_iso03": 0.6600441501103753,
      "mean_cluster_iso_03": 1.2133492231369019,
      "median_cluster_iso_03": 0.9550588726997375,
      "mean_cluster_iso_03_emcal": 4.853787899017334,
      "median_cluster_iso_03_emcal": 4.746524810791016,
      "mean_cluster_iso_03_hcalin": 0.29375869035720825,
      "median_cluster_iso_03_hcalin": 0.23091597855091095,
      "mean_cluster_iso_03_hcalout": 0.2873546779155731,
      "median_cluster_iso_03_hcalout": 0.2162141650915146,
      "mean_cluster_iso_04": 1.3642680644989014,
      "median_cluster_iso_04": 1.0990605354309082,
      "mean_cluster_iso_04_emcal": 8.187751770019531,
      "median_cluster_iso_04_emcal": 8.275579452514648,
      "mean_cluster_iso_04_hcalin": 0.3221103847026825,
      "median_cluster_iso_04_hcalin": 0.25609007477760315,
      "mean_cluster_iso_04_hcalout": 0.4436279833316803,
      "median_cluster_iso_04_hcalout": 0.35610607266426086,
      "n_exact": 1359,
      "n_pass_exact": 895,
      "pass_frac_exact": 0.6585724797645327,
      "mean_cluster_Et": 18.893249646454194
    },
    "20to22": {
      "n": 732,
      "iso_cut": 1.4114706,
      "n_pass_iso03": 485,
      "pass_frac_iso03": 0.662568306010929,
      "mean_cluster_iso_03": 1.2632209062576294,
      "median_cluster_iso_03": 1.0349161624908447,
      "mean_cluster_iso_03_emcal": 4.834989070892334,
      "median_cluster_iso_03_emcal": 4.757308006286621,
      "mean_cluster_iso_03_hcalin": 0.350373238325119,
      "median_cluster_iso_03_hcalin": 0.26208585500717163,
      "mean_cluster_iso_03_hcalout": 0.3010421693325043,
      "median_cluster_iso_03_hcalout": 0.23112767934799194,
      "mean_cluster_iso_04": 1.4344302415847778,
      "median_cluster_iso_04": 1.2363073825836182,
      "mean_cluster_iso_04_emcal": 8.231890678405762,
      "median_cluster_iso_04_emcal": 8.384835243225098,
      "mean_cluster_iso_04_hcalin": 0.38167884945869446,
      "median_cluster_iso_04_hcalin": 0.2962207496166229,
      "mean_cluster_iso_04_hcalout": 0.4535072147846222,
      "median_cluster_iso_04_hcalout": 0.3663274049758911,
      "n_exact": 732,
      "n_pass_exact": 487,
      "pass_frac_exact": 0.6653005464480874,
      "mean_cluster_Et": 20.892435376109972
    },
    "22to24": {
      "n": 414,
      "iso_cut": 1.4980778,
      "n_pass_iso03": 286,
      "pass_frac_iso03": 0.6908212560386473,
      "mean_cluster_iso_03": 1.2798980474472046,
      "median_cluster_iso_03": 1.0432493686676025,
      "mean_cluster_iso_03_emcal": 4.835922718048096,
      "median_cluster_iso_03_emcal": 4.755527496337891,
      "mean_cluster_iso_03_hcalin": 0.3649933338165283,
      "median_cluster_iso_03_hcalin": 0.295768678188324,
      "mean_cluster_iso_03_hcalout": 0.29989132285118103,
      "median_cluster_iso_03_hcalout": 0.23311792314052582,
      "mean_cluster_iso_04": 1.4474436044692993,
      "median_cluster_iso_04": 1.2574145793914795,
      "mean_cluster_iso_04_emcal": 8.223036766052246,
      "median_cluster_iso_04_emcal": 8.360222816467285,
      "mean_cluster_iso_04_hcalin": 0.39500266313552856,
      "median_cluster_iso_04_hcalin": 0.3195236325263977,
      "mean_cluster_iso_04_hcalout": 0.4530753791332245,
      "median_cluster_iso_04_hcalout": 0.3674951493740082,
      "n_exact": 414,
      "n_pass_exact": 284,
      "pass_frac_exact": 0.6859903381642513,
      "mean_cluster_Et": 22.889151900286837
    },
    "24to26": {
      "n": 198,
      "iso_cut": 1.584685,
      "n_pass_iso03": 146,
      "pass_frac_iso03": 0.7373737373737373,
      "mean_cluster_iso_03": 1.2204093933105469,
      "median_cluster_iso_03": 1.0296056270599365,
      "mean_cluster_iso_03_emcal": 4.6940598487854,
      "median_cluster_iso_03_emcal": 4.6764373779296875,
      "mean_cluster_iso_03_hcalin": 0.41616058349609375,
      "median_cluster_iso_03_hcalin": 0.3261021673679352,
      "mean_cluster_iso_03_hcalout": 0.3282860517501831,
      "median_cluster_iso_03_hcalout": 0.2605099678039551,
      "mean_cluster_iso_04": 1.3559730052947998,
      "median_cluster_iso_04": 1.1173866987228394,
      "mean_cluster_iso_04_emcal": 8.001322746276855,
      "median_cluster_iso_04_emcal": 8.184321403503418,
      "mean_cluster_iso_04_hcalin": 0.44789284467697144,
      "median_cluster_iso_04_hcalin": 0.3582528233528137,
      "mean_cluster_iso_04_hcalout": 0.5042482018470764,
      "median_cluster_iso_04_hcalout": 0.40902823209762573,
      "n_exact": 198,
      "n_pass_exact": 144,
      "pass_frac_exact": 0.7272727272727273,
      "mean_cluster_Et": 24.910445396346276
    },
    "26to28": {
      "n": 126,
      "iso_cut": 1.6712922,
      "n_pass_iso03": 94,
      "pass_frac_iso03": 0.746031746031746,
      "mean_cluster_iso_03": 1.2740780115127563,
      "median_cluster_iso_03": 1.0670760869979858,
      "mean_cluster_iso_03_emcal": 4.876307487487793,
      "median_cluster_iso_03_emcal": 4.794299125671387,
      "mean_cluster_iso_03_hcalin": 0.37150874733924866,
      "median_cluster_iso_03_hcalin": 0.2839415669441223,
      "mean_cluster_iso_03_hcalout": 0.3577394187450409,
      "median_cluster_iso_03_hcalout": 0.25876668095588684,
      "mean_cluster_iso_04": 1.455915093421936,
      "median_cluster_iso_04": 1.267928123474121,
      "mean_cluster_iso_04_emcal": 8.445209503173828,
      "median_cluster_iso_04_emcal": 8.386778831481934,
      "mean_cluster_iso_04_hcalin": 0.40153756737709045,
      "median_cluster_iso_04_hcalin": 0.3041653037071228,
      "mean_cluster_iso_04_hcalout": 0.5086190104484558,
      "median_cluster_iso_04_hcalout": 0.4020860195159912,
      "n_exact": 126,
      "n_pass_exact": 94,
      "pass_frac_exact": 0.746031746031746,
      "mean_cluster_Et": 26.851529075985862
    },
    "28to32": {
      "n": 103,
      "iso_cut": 1.8012029999999999,
      "n_pass_iso03": 69,
      "pass_frac_iso03": 0.6699029126213593,
      "mean_cluster_iso_03": 1.5812139511108398,
      "median_cluster_iso_03": 1.3407715559005737,
      "mean_cluster_iso_03_emcal": 4.900319576263428,
      "median_cluster_iso_03_emcal": 4.792488098144531,
      "mean_cluster_iso_03_hcalin": 0.561479389667511,
      "median_cluster_iso_03_hcalin": 0.40444815158843994,
      "mean_cluster_iso_03_hcalout": 0.4221619665622711,
      "median_cluster_iso_03_hcalout": 0.30943596363067627,
      "mean_cluster_iso_04": 1.7057397365570068,
      "median_cluster_iso_04": 1.4661318063735962,
      "mean_cluster_iso_04_emcal": 8.311792373657227,
      "median_cluster_iso_04_emcal": 8.329599380493164,
      "mean_cluster_iso_04_hcalin": 0.5918506383895874,
      "median_cluster_iso_04_hcalin": 0.42681068181991577,
      "mean_cluster_iso_04_hcalout": 0.5727196931838989,
      "median_cluster_iso_04_hcalout": 0.4281623363494873,
      "n_exact": 103,
      "n_pass_exact": 68,
      "pass_frac_exact": 0.6601941747572816,
      "mean_cluster_Et": 29.557848291489684
    },
    "32to36": {
      "n": 25,
      "iso_cut": 1.9744173999999999,
      "n_pass_iso03": 22,
      "pass_frac_iso03": 0.88,
      "mean_cluster_iso_03": 1.2605485916137695,
      "median_cluster_iso_03": 1.0921251773834229,
      "mean_cluster_iso_03_emcal": 4.500341415405273,
      "median_cluster_iso_03_emcal": 4.554450988769531,
      "mean_cluster_iso_03_hcalin": 0.521860659122467,
      "median_cluster_iso_03_hcalin": 0.4830018877983093,
      "mean_cluster_iso_03_hcalout": 0.42613548040390015,
      "median_cluster_iso_03_hcalout": 0.35714346170425415,
      "mean_cluster_iso_04": 1.3301693201065063,
      "median_cluster_iso_04": 1.2958247661590576,
      "mean_cluster_iso_04_emcal": 7.781318187713623,
      "median_cluster_iso_04_emcal": 7.8255615234375,
      "mean_cluster_iso_04_hcalin": 0.5501468181610107,
      "median_cluster_iso_04_hcalin": 0.5016748309135437,
      "mean_cluster_iso_04_hcalout": 0.6237128973007202,
      "median_cluster_iso_04_hcalout": 0.4919110834598541,
      "n_exact": 25,
      "n_pass_exact": 22,
      "pass_frac_exact": 0.88,
      "mean_cluster_Et": 34.0348828125
    },
    "8to36": {
      "n": 87717,
      "iso_cut": 1.1083454,
      "n_pass_iso03": 47705,
      "pass_frac_iso03": 0.5438512489027213,
      "mean_cluster_iso_03": 1.3862932920455933,
      "median_cluster_iso_03": 1.0004589557647705,
      "mean_cluster_iso_03_emcal": 5.151094436645508,
      "median_cluster_iso_03_emcal": 4.857387542724609,
      "mean_cluster_iso_03_hcalin": 0.21271853148937225,
      "median_cluster_iso_03_hcalin": 0.15261247754096985,
      "mean_cluster_iso_03_hcalout": 0.2533378601074219,
      "median_cluster_iso_03_hcalout": 0.19272273778915405,
      "mean_cluster_iso_04": 1.5314199924468994,
      "median_cluster_iso_04": 1.1873546838760376,
      "mean_cluster_iso_04_emcal": 8.484238624572754,
      "median_cluster_iso_04_emcal": 8.431382179260254,
      "mean_cluster_iso_04_hcalin": 0.24099621176719666,
      "median_cluster_iso_04_hcalin": 0.17884643375873566,
      "mean_cluster_iso_04_hcalout": 0.3980216681957245,
      "median_cluster_iso_04_hcalout": 0.3233420252799988,
      "n_exact": 87717,
      "n_pass_exact": 44089,
      "pass_frac_exact": 0.5026277688475438,
      "mean_cluster_Et": 11.43253819812579
    }
  },
  "bad": {
    "8to10": {
      "n": 10,
      "iso_cut": 0.8918273999999999,
      "n_pass_iso03": 2,
      "pass_frac_iso03": 0.2,
      "mean_cluster_iso_03": 1.9328603744506836,
      "median_cluster_iso_03": 2.1183738708496094,
      "mean_cluster_iso_03_emcal": 5.025486946105957,
      "median_cluster_iso_03_emcal": 5.164588928222656,
      "mean_cluster_iso_03_hcalin": 0.30318841338157654,
      "median_cluster_iso_03_hcalin": 0.2120220959186554,
      "mean_cluster_iso_03_hcalout": 0.6366159915924072,
      "median_cluster_iso_03_hcalout": 0.3686608076095581,
      "mean_cluster_iso_04": 2.33182692527771,
      "median_cluster_iso_04": 2.4787683486938477,
      "mean_cluster_iso_04_emcal": 8.45366096496582,
      "median_cluster_iso_04_emcal": 8.68370246887207,
      "mean_cluster_iso_04_hcalin": 0.3374081254005432,
      "median_cluster_iso_04_hcalin": 0.23510220646858215,
      "mean_cluster_iso_04_hcalout": 0.9238700866699219,
      "median_cluster_iso_04_hcalout": 0.7730493545532227,
      "n_exact": 10,
      "n_pass_exact": 1,
      "pass_frac_exact": 0.1,
      "mean_cluster_Et": 8.943517208099365
    },
    "10to12": {
      "n": 6,
      "iso_cut": 0.9784345999999999,
      "n_pass_iso03": 4,
      "pass_frac_iso03": 0.6666666666666666,
      "mean_cluster_iso_03": 1.4939473867416382,
      "median_cluster_iso_03": 0.7896391749382019,
      "mean_cluster_iso_03_emcal": 4.984111785888672,
      "median_cluster_iso_03_emcal": 5.104991436004639,
      "mean_cluster_iso_03_hcalin": 0.1870279461145401,
      "median_cluster_iso_03_hcalin": 0.12211811542510986,
      "mean_cluster_iso_03_hcalout": 0.5288593173027039,
      "median_cluster_iso_03_hcalout": 0.19989944994449615,
      "mean_cluster_iso_04": 1.6198824644088745,
      "median_cluster_iso_04": 1.1288601160049438,
      "mean_cluster_iso_04_emcal": 8.300812721252441,
      "median_cluster_iso_04_emcal": 8.9154052734375,
      "mean_cluster_iso_04_hcalin": 0.21347485482692719,
      "median_cluster_iso_04_hcalin": 0.13534069061279297,
      "mean_cluster_iso_04_hcalout": 0.7051573395729065,
      "median_cluster_iso_04_hcalout": 0.3643283247947693,
      "n_exact": 6,
      "n_pass_exact": 4,
      "pass_frac_exact": 0.6666666666666666,
      "mean_cluster_Et": 10.73680067062378
    },
    "12to14": {
      "n": 2,
      "iso_cut": 1.0650418,
      "n_pass_iso03": 1,
      "pass_frac_iso03": 0.5,
      "mean_cluster_iso_03": 3.7602171897888184,
      "median_cluster_iso_03": 3.7602171897888184,
      "mean_cluster_iso_03_emcal": 7.856473445892334,
      "median_cluster_iso_03_emcal": 7.856473445892334,
      "mean_cluster_iso_03_hcalin": 0.245886892080307,
      "median_cluster_iso_03_hcalin": 0.245886892080307,
      "mean_cluster_iso_03_hcalout": 0.0915231704711914,
      "median_cluster_iso_03_hcalout": 0.0915231704711914,
      "mean_cluster_iso_04": 3.81583309173584,
      "median_cluster_iso_04": 3.81583309173584,
      "mean_cluster_iso_04_emcal": 11.344032287597656,
      "median_cluster_iso_04_emcal": 11.344032287597656,
      "mean_cluster_iso_04_hcalin": 0.39482054114341736,
      "median_cluster_iso_04_hcalin": 0.39482054114341736,
      "mean_cluster_iso_04_hcalout": 0.44424182176589966,
      "median_cluster_iso_04_hcalout": 0.44424182176589966,
      "n_exact": 2,
      "n_pass_exact": 1,
      "pass_frac_exact": 0.5,
      "mean_cluster_Et": 12.260734558105469
    },
    "14to16": {
      "n": 0,
      "iso_cut": 1.151649,
      "n_pass_iso03": 0,
      "pass_frac_iso03": NaN,
      "mean_cluster_iso_03": NaN,
      "median_cluster_iso_03": NaN,
      "mean_cluster_iso_03_emcal": NaN,
      "median_cluster_iso_03_emcal": NaN,
      "mean_cluster_iso_03_hcalin": NaN,
      "median_cluster_iso_03_hcalin": NaN,
      "mean_cluster_iso_03_hcalout": NaN,
      "median_cluster_iso_03_hcalout": NaN,
      "mean_cluster_iso_04": NaN,
      "median_cluster_iso_04": NaN,
      "mean_cluster_iso_04_emcal": NaN,
      "median_cluster_iso_04_emcal": NaN,
      "mean_cluster_iso_04_hcalin": NaN,
      "median_cluster_iso_04_hcalin": NaN,
      "mean_cluster_iso_04_hcalout": NaN,
      "median_cluster_iso_04_hcalout": NaN,
      "n_exact": 0,
      "n_pass_exact": 0,
      "pass_frac_exact": NaN,
      "mean_cluster_Et": NaN
    },
    "16to18": {
      "n": 0,
      "iso_cut": 1.2382562,
      "n_pass_iso03": 0,
      "pass_frac_iso03": NaN,
      "mean_cluster_iso_03": NaN,
      "median_cluster_iso_03": NaN,
      "mean_cluster_iso_03_emcal": NaN,
      "median_cluster_iso_03_emcal": NaN,
      "mean_cluster_iso_03_hcalin": NaN,
      "median_cluster_iso_03_hcalin": NaN,
      "mean_cluster_iso_03_hcalout": NaN,
      "median_cluster_iso_03_hcalout": NaN,
      "mean_cluster_iso_04": NaN,
      "median_cluster_iso_04": NaN,
      "mean_cluster_iso_04_emcal": NaN,
      "median_cluster_iso_04_emcal": NaN,
      "mean_cluster_iso_04_hcalin": NaN,
      "median_cluster_iso_04_hcalin": NaN,
      "mean_cluster_iso_04_hcalout": NaN,
      "median_cluster_iso_04_hcalout": NaN,
      "n_exact": 0,
      "n_pass_exact": 0,
      "pass_frac_exact": NaN,
      "mean_cluster_Et": NaN
    },
    "18to20": {
      "n": 0,
      "iso_cut": 1.3248634,
      "n_pass_iso03": 0,
      "pass_frac_iso03": NaN,
      "mean_cluster_iso_03": NaN,
      "median_cluster_iso_03": NaN,
      "mean_cluster_iso_03_emcal": NaN,
      "median_cluster_iso_03_emcal": NaN,
      "mean_cluster_iso_03_hcalin": NaN,
      "median_cluster_iso_03_hcalin": NaN,
      "mean_cluster_iso_03_hcalout": NaN,
      "median_cluster_iso_03_hcalout": NaN,
      "mean_cluster_iso_04": NaN,
      "median_cluster_iso_04": NaN,
      "mean_cluster_iso_04_emcal": NaN,
      "median_cluster_iso_04_emcal": NaN,
      "mean_cluster_iso_04_hcalin": NaN,
      "median_cluster_iso_04_hcalin": NaN,
      "mean_cluster_iso_04_hcalout": NaN,
      "median_cluster_iso_04_hcalout": NaN,
      "n_exact": 0,
      "n_pass_exact": 0,
      "pass_frac_exact": NaN,
      "mean_cluster_Et": NaN
    },
    "20to22": {
      "n": 0,
      "iso_cut": 1.4114706,
      "n_pass_iso03": 0,
      "pass_frac_iso03": NaN,
      "mean_cluster_iso_03": NaN,
      "median_cluster_iso_03": NaN,
      "mean_cluster_iso_03_emcal": NaN,
      "median_cluster_iso_03_emcal": NaN,
      "mean_cluster_iso_03_hcalin": NaN,
      "median_cluster_iso_03_hcalin": NaN,
      "mean_cluster_iso_03_hcalout": NaN,
      "median_cluster_iso_03_hcalout": NaN,
      "mean_cluster_iso_04": NaN,
      "median_cluster_iso_04": NaN,
      "mean_cluster_iso_04_emcal": NaN,
      "median_cluster_iso_04_emcal": NaN,
      "mean_cluster_iso_04_hcalin": NaN,
      "median_cluster_iso_04_hcalin": NaN,
      "mean_cluster_iso_04_hcalout": NaN,
      "median_cluster_iso_04_hcalout": NaN,
      "n_exact": 0,
      "n_pass_exact": 0,
      "pass_frac_exact": NaN,
      "mean_cluster_Et": NaN
    },
    "22to24": {
      "n": 0,
      "iso_cut": 1.4980778,
      "n_pass_iso03": 0,
      "pass_frac_iso03": NaN,
      "mean_cluster_iso_03": NaN,
      "median_cluster_iso_03": NaN,
      "mean_cluster_iso_03_emcal": NaN,
      "median_cluster_iso_03_emcal": NaN,
      "mean_cluster_iso_03_hcalin": NaN,
      "median_cluster_iso_03_hcalin": NaN,
      "mean_cluster_iso_03_hcalout": NaN,
      "median_cluster_iso_03_hcalout": NaN,
      "mean_cluster_iso_04": NaN,
      "median_cluster_iso_04": NaN,
      "mean_cluster_iso_04_emcal": NaN,
      "median_cluster_iso_04_emcal": NaN,
      "mean_cluster_iso_04_hcalin": NaN,
      "median_cluster_iso_04_hcalin": NaN,
      "mean_cluster_iso_04_hcalout": NaN,
      "median_cluster_iso_04_hcalout": NaN,
      "n_exact": 0,
      "n_pass_exact": 0,
      "pass_frac_exact": NaN,
      "mean_cluster_Et": NaN
    },
    "24to26": {
      "n": 0,
      "iso_cut": 1.584685,
      "n_pass_iso03": 0,
      "pass_frac_iso03": NaN,
      "mean_cluster_iso_03": NaN,
      "median_cluster_iso_03": NaN,
      "mean_cluster_iso_03_emcal": NaN,
      "median_cluster_iso_03_emcal": NaN,
      "mean_cluster_iso_03_hcalin": NaN,
      "median_cluster_iso_03_hcalin": NaN,
      "mean_cluster_iso_03_hcalout": NaN,
      "median_cluster_iso_03_hcalout": NaN,
      "mean_cluster_iso_04": NaN,
      "median_cluster_iso_04": NaN,
      "mean_cluster_iso_04_emcal": NaN,
      "median_cluster_iso_04_emcal": NaN,
      "mean_cluster_iso_04_hcalin": NaN,
      "median_cluster_iso_04_hcalin": NaN,
      "mean_cluster_iso_04_hcalout": NaN,
      "median_cluster_iso_04_hcalout": NaN,
      "n_exact": 0,
      "n_pass_exact": 0,
      "pass_frac_exact": NaN,
      "mean_cluster_Et": NaN
    },
    "26to28": {
      "n": 0,
      "iso_cut": 1.6712922,
      "n_pass_iso03": 0,
      "pass_frac_iso03": NaN,
      "mean_cluster_iso_03": NaN,
      "median_cluster_iso_03": NaN,
      "mean_cluster_iso_03_emcal": NaN,
      "median_cluster_iso_03_emcal": NaN,
      "mean_cluster_iso_03_hcalin": NaN,
      "median_cluster_iso_03_hcalin": NaN,
      "mean_cluster_iso_03_hcalout": NaN,
      "median_cluster_iso_03_hcalout": NaN,
      "mean_cluster_iso_04": NaN,
      "median_cluster_iso_04": NaN,
      "mean_cluster_iso_04_emcal": NaN,
      "median_cluster_iso_04_emcal": NaN,
      "mean_cluster_iso_04_hcalin": NaN,
      "median_cluster_iso_04_hcalin": NaN,
      "mean_cluster_iso_04_hcalout": NaN,
      "median_cluster_iso_04_hcalout": NaN,
      "n_exact": 0,
      "n_pass_exact": 0,
      "pass_frac_exact": NaN,
      "mean_cluster_Et": NaN
    },
    "28to32": {
      "n": 0,
      "iso_cut": 1.8012029999999999,
      "n_pass_iso03": 0,
      "pass_frac_iso03": NaN,
      "mean_cluster_iso_03": NaN,
      "median_cluster_iso_03": NaN,
      "mean_cluster_iso_03_emcal": NaN,
      "median_cluster_iso_03_emcal": NaN,
      "mean_cluster_iso_03_hcalin": NaN,
      "median_cluster_iso_03_hcalin": NaN,
      "mean_cluster_iso_03_hcalout": NaN,
      "median_cluster_iso_03_hcalout": NaN,
      "mean_cluster_iso_04": NaN,
      "median_cluster_iso_04": NaN,
      "mean_cluster_iso_04_emcal": NaN,
      "median_cluster_iso_04_emcal": NaN,
      "mean_cluster_iso_04_hcalin": NaN,
      "median_cluster_iso_04_hcalin": NaN,
      "mean_cluster_iso_04_hcalout": NaN,
      "median_cluster_iso_04_hcalout": NaN,
      "n_exact": 0,
      "n_pass_exact": 0,
      "pass_frac_exact": NaN,
      "mean_cluster_Et": NaN
    },
    "32to36": {
      "n": 0,
      "iso_cut": 1.9744173999999999,
      "n_pass_iso03": 0,
      "pass_frac_iso03": NaN,
      "mean_cluster_iso_03": NaN,
      "median_cluster_iso_03": NaN,
      "mean_cluster_iso_03_emcal": NaN,
      "median_cluster_iso_03_emcal": NaN,
      "mean_cluster_iso_03_hcalin": NaN,
      "median_cluster_iso_03_hcalin": NaN,
      "mean_cluster_iso_03_hcalout": NaN,
      "median_cluster_iso_03_hcalout": NaN,
      "mean_cluster_iso_04": NaN,
      "median_cluster_iso_04": NaN,
      "mean_cluster_iso_04_emcal": NaN,
      "median_cluster_iso_04_emcal": NaN,
      "mean_cluster_iso_04_hcalin": NaN,
      "median_cluster_iso_04_hcalin": NaN,
      "mean_cluster_iso_04_hcalout": NaN,
      "median_cluster_iso_04_hcalout": NaN,
      "n_exact": 0,
      "n_pass_exact": 0,
      "pass_frac_exact": NaN,
      "mean_cluster_Et": NaN
    },
    "8to36": {
      "n": 18,
      "iso_cut": 1.1083454,
      "n_pass_iso03": 9,
      "pass_frac_iso03": 0.5,
      "mean_cluster_iso_03": 1.989595651626587,
      "median_cluster_iso_03": 1.1142631769180298,
      "mean_cluster_iso_03_emcal": 5.326249122619629,
      "median_cluster_iso_03_emcal": 5.241759300231934,
      "mean_cluster_iso_03_hcalin": 0.2581014037132263,
      "median_cluster_iso_03_hcalin": 0.17099326848983765,
      "mean_cluster_iso_03_hcalout": 0.5401312708854675,
      "median_cluster_iso_03_hcalout": 0.27162155508995056,
      "mean_cluster_iso_04": 2.259401798248291,
      "median_cluster_iso_04": 1.6491079330444336,
      "mean_cluster_iso_04_emcal": 8.72386360168457,
      "median_cluster_iso_04_emcal": 9.002462387084961,
      "mean_cluster_iso_04_hcalin": 0.3024761974811554,
      "median_cluster_iso_04_hcalin": 0.20214596390724182,
      "mean_cluster_iso_04_hcalout": 0.7976738214492798,
      "median_cluster_iso_04_hcalout": 0.4942401051521301,
      "n_exact": 18,
      "n_pass_exact": 6,
      "pass_frac_exact": 0.3333333333333333,
      "mean_cluster_Et": 9.90985827975803
    }
  }
}